dbhelperutil/__init__.py
dbhelperutil/database_handler.py
dbhelperutil/easy_oracle.py
dbhelperutil/unittests/__init__.py
dbhelperutil/unittests/test_database_handler.py
dbhelperutil-1.1.0.dist-info/DESCRIPTION.rst
dbhelperutil-1.1.0.dist-info/METADATA
dbhelperutil-1.1.0.dist-info/RECORD
dbhelperutil-1.1.0.dist-info/WHEEL
dbhelperutil-1.1.0.dist-info/entry_points.txt
dbhelperutil-1.1.0.dist-info/metadata.json
dbhelperutil-1.1.0.dist-info/top_level.txt
